fantasy/__init__.py
fantasy/bootstrap.py
fantasy/celery.py
fantasy/cli.py
fantasy/error_handler.py
fantasy/flaskparser.py
fantasy/i18n.py
fantasy/random.py
fantasy_command/__init__.py
fantasy_command/migrate.py
fantasy_pytest/__init__.py
fantasy_pytest/fixtures.py
fantasy_pytest/marks.py
fantasy_utils/__init__.py
fantasy_utils/dbhelper.py
fantasy_utils/dict_utils.py
tests/mock_api_v1/__init__.py
tests/mock_api_v1/apis.py
tests/test_utils/__init__.py
tests/test_utils/test_utils.py
flask_fantasy-0.4.2.dist-info/LICENSE
flask_fantasy-0.4.2.dist-info/METADATA
flask_fantasy-0.4.2.dist-info/WHEEL
flask_fantasy-0.4.2.dist-info/entry_points.txt
flask_fantasy-0.4.2.dist-info/top_level.txt
flask_fantasy-0.4.2.dist-info/RECORD
