Metadata-Version: 2.1
Name: flask-fantasy
Version: 0.4.2
Summary: A lazy web-framework based on Flask
Home-page: https://github.com/9nix00/fantasy
Author: WANG WENPEI
Author-email: stormxx@1024.engineer
License: MIT
Download-URL: https://github.com/9nix00/fantasy/archive/v0.4.2.tar.gz
Keywords: fantasy,flask
Platform: UNKNOWN
Classifier: Framework :: Pytest
Requires-Dist: celery (==4.4.0)
Requires-Dist: blinker (==1.4)
Requires-Dist: raven (==6.10.0)
Requires-Dist: requests (==2.22.0)
Requires-Dist: redis (==3.3.11)
Requires-Dist: webargs (==5.5.2)
Requires-Dist: PyMySQL (==0.9.3)
Requires-Dist: python-dateutil (==2.8.1)
Requires-Dist: Flask (==1.1.1)
Requires-Dist: Flask-SQLAlchemy (==2.4.1)
Requires-Dist: flask-prometheus-metrics (==1.0.0)
Requires-Dist: flask-migrate (==2.5.2)
Requires-Dist: Flask-Admin (==1.5.5)
Requires-Dist: flask-cors (==3.0.8)
Requires-Dist: flask-babel (==1.0.0)
Requires-Dist: SQLAlchemy-Utils (==0.36.1)
